dna/__init__.py
dna/__main__.py
dna/coding.py
dna/core.py
dna/yaml_io.py
dnadsl-0.4.0.dist-info/licenses/LICENSE
dnadsl-0.4.0.dist-info/METADATA
dnadsl-0.4.0.dist-info/WHEEL
dnadsl-0.4.0.dist-info/entry_points.txt
dnadsl-0.4.0.dist-info/top_level.txt
dnadsl-0.4.0.dist-info/RECORD
