Metadata-Version: 2.4
Name: dnadsl
Version: 0.4.0
Summary: DNA: a domain-specific language (transcription between UTF-8 text and DNA bases) based on YAML.
Author-email: Zhan Ziyuan <ziyuanzhan@mail.nankai.edu.cn>
Maintainer-email: Zhan Ziyuan <ziyuanzhan@mail.nankai.edu.cn>
License: GNU GPLv3
Project-URL: Homepage, https://github.com/project-aico/dna
Project-URL: Bug Tracker, https://github.com/project-aico/dna/issues
Classifier: Environment :: Console
Classifier: License :: OSI Approved :: GNU General Public License v3 (GPLv3)
Classifier: Operating System :: Microsoft :: Windows
Classifier: Operating System :: POSIX :: Linux
Classifier: Programming Language :: Python :: 3.10
Classifier: Programming Language :: Python :: 3.11
Classifier: Programming Language :: Python :: 3.12
Classifier: Programming Language :: Python :: 3.13
Classifier: Topic :: Scientific/Engineering :: Bio-Informatics
Classifier: Topic :: Security :: Cryptography
Requires-Python: >=3.10
License-File: LICENSE
Requires-Dist: PyYAML>=6.0.2
Dynamic: license-file
